mybassm/__init__.py
mybassm/mybassm.py
mybassm-0.1.1.dist-info/AUTHORS.rst
mybassm-0.1.1.dist-info/LICENSE
mybassm-0.1.1.dist-info/METADATA
mybassm-0.1.1.dist-info/WHEEL
mybassm-0.1.1.dist-info/top_level.txt
mybassm-0.1.1.dist-info/RECORD
