Metadata-Version: 2.1
Name: mybassm
Version: 0.1.1
Summary: it is a packgae that does bass modeling 
Home-page: https://github.com/anukzak22/mybassm
Author: Anahit Zakaryan
Author-email: anukzak@gmail.com
License: MIT license
Keywords: mybassm
Classifier: Development Status :: 2 - Pre-Alpha
Classifier: Intended Audience :: Developers
Classifier: License :: OSI Approved :: MIT License
Classifier: Natural Language :: English
Classifier: Programming Language :: Python :: 3
Classifier: Programming Language :: Python :: 3.6
Classifier: Programming Language :: Python :: 3.7
Classifier: Programming Language :: Python :: 3.8
Requires-Python: >=3.6
License-File: LICENSE
License-File: AUTHORS.rst
